third_python_package/hello.py
third_python_package/harmonic_mean.pyx
third_python_package/__init__.py
third_python_package/harmony.py
third_python_package/data.json
third_python_package/harmonic_mean.cpython-312-darwin.so
third_python_package/py.typed
third_python_package/harmonic_mean.c
third_python_package/harmonic_mean.pyi
third_python_package/slow_harmonic_mean.py
third_python_package_tpotjj-0.0.3.dist-info/RECORD
third_python_package_tpotjj-0.0.3.dist-info/LICENSE
third_python_package_tpotjj-0.0.3.dist-info/WHEEL
third_python_package_tpotjj-0.0.3.dist-info/entry_points.txt
third_python_package_tpotjj-0.0.3.dist-info/top_level.txt
third_python_package_tpotjj-0.0.3.dist-info/METADATA
