Metadata-Version: 2.1
Name: third-python-package-tpotjj
Version: 0.0.3
Summary: This package does amazing things.
Home-page: https://github.com/tpotjj/third-python-package
Author: Joris Jansen
Author-email: "Joris Jansen" <github@tpotjj.com>
License: MIT
Classifier: License :: OSI Approved :: MIT License
License-File: LICENSE
Requires-Dist: termcolor <3,>=2.3.0
